condreg_cpp.cpython-310-darwin.so
condreg/__init__.py
condreg/condreg_loader.py
condreg/init_condreg.py
condreg/init_path.py
condreg-0.1.3.dist-info/LICENSE
condreg-0.1.3.dist-info/METADATA
condreg-0.1.3.dist-info/WHEEL
condreg-0.1.3.dist-info/top_level.txt
condreg-0.1.3.dist-info/RECORD
