Metadata-Version: 2.1
Name: condreg
Version: 0.1.3
Summary: Condition Number Regularized Covariance Estimation
Home-page: https://github.com/dddlab/CondReg
Author: Sang Yun Oh, Lixing Guo
Author-email: Sang Yun Oh <syoh@ucsb.edu>, Lixing Guo <lixing_guo@ucsb.edu>
License: MIT
Project-URL: Homepage, https://github.com/dddlab/CondReg
Project-URL: Bug Tracker, https://github.com/dddlab/CondReg/issues
Project-URL: Documentation, https://github.com/dddlab/CondReg/blob/main/README.md
Project-URL: Source Code, https://github.com/dddlab/CondReg
Classifier: Development Status :: 4 - Beta
Classifier: Intended Audience :: Science/Research
Classifier: Intended Audience :: Developers
Classifier: Intended Audience :: Education
Classifier: Intended Audience :: Financial and Insurance Industry
Classifier: Topic :: Scientific/Engineering
Classifier: Topic :: Scientific/Engineering :: Mathematics
Classifier: Topic :: Scientific/Engineering :: Artificial Intelligence
Classifier: Topic :: Scientific/Engineering :: Information Analysis
Classifier: Topic :: Software Development :: Libraries
Classifier: Topic :: Software Development :: Libraries :: Python Modules
Classifier: License :: OSI Approved :: MIT License
Classifier: Programming Language :: Python
Classifier: Programming Language :: Python :: 3
Classifier: Programming Language :: Python :: 3.6
Classifier: Programming Language :: Python :: 3.7
Classifier: Programming Language :: Python :: 3.8
Classifier: Programming Language :: Python :: 3.9
Classifier: Programming Language :: Python :: 3.10
Classifier: Programming Language :: Python :: 3.11
Classifier: Programming Language :: C++
Classifier: Operating System :: OS Independent
Classifier: Operating System :: Microsoft :: Windows
Classifier: Operating System :: POSIX :: Linux
Classifier: Operating System :: MacOS
Classifier: Natural Language :: English
Classifier: Framework :: Jupyter
Requires-Python: >=3.6
License-File: LICENSE
Requires-Dist: numpy>=1.18.0
